LICENSE
MANIFEST.in
README.rst
buildout.cfg
requirements.txt
setup.py
version.txt
bob/__init__.py
bob.db.refuge.egg-info/PKG-INFO
bob.db.refuge.egg-info/SOURCES.txt
bob.db.refuge.egg-info/dependency_links.txt
bob.db.refuge.egg-info/entry_points.txt
bob.db.refuge.egg-info/not-zip-safe
bob.db.refuge.egg-info/requires.txt
bob.db.refuge.egg-info/top_level.txt
bob/db/__init__.py
bob/db/refuge/__init__.py
bob/db/refuge/checkfiles.py
bob/db/refuge/create.py
bob/db/refuge/driver.py
bob/db/refuge/models.py
bob/db/refuge/query.py
bob/db/refuge/refuge_db_default_cup.json
bob/db/refuge/refuge_db_default_od.json
bob/db/refuge/refuge_test.csv
bob/db/refuge/refuge_train.csv
bob/db/refuge/test.py
doc/guide.rst
doc/index.rst
doc/links.rst
doc/py_api.rst
doc/img/bob-128x128.png
doc/img/bob-favicon.ico
doc/img/bob-logo.png